pipeline.v
module pipeline_4(zout,rs1,rs2,rd,clk1,clk2,addr,func);
    input [7:0] rs1,rs2,rd,func;
    input [3:0] addr;
    input clk1, clk2; //two phased clock
    output [7:0] zout;

    reg [15:0] L12_A, L12_B, L23_Z, L34_Z;
    reg [7:0] L12_addr, L23_addr, L34_addr;
    reg [3:0] L12_func, L23_rd, L12_rd;

    reg [15:0] regbank [0:15];
    reg [15:0] mem [0:255];

    assign zout = L34_Z;
    always @(posedge clk1) begin
        // Stage 1: Read from registers
        L12_A <= #2 regbank[rs1];
        L12_B <= #2 regbank[rs2];
        L12_rd <= #2 rd;
        L12_addr <= #2 addr;
        L12_func <= #2 func;   /*stage 1*/
    end
    always @(negedge clk2) begin
        // Stage 2: Perform operation
        case (L12_func)
            4'b0000: L23_Z <= #2 L12_A + L12_B; // ADD
            4'b0001: L23_Z <= #2 L12_A - L12_B; // SUB
            4'b0010: L23_Z <= #2 L12_A & L12_B; // AND
            4'b0011: L23_Z <= #2 L12_A; // SELA
            4'b0100: L23_Z <= #2 L12_B; // SELB
            4'b0101: L23_Z <= #2 ~L12_A;        // NOT
            4'b0110: L23_Z <= #2 L12_A | L12_B; // OR
            4'b0111: L23_Z <= #2 L12_A ^ L12_B; // XOR
            4'b1000: L23_Z <= #2 mem[L12_addr]; // LOAD
            4'b1001: mem[L12_addr] <= #2 L12_A; // STORE
            default: L23_Z <= #2 16'h0000;      // Default case
        endcase
        L23_addr <= #2 L12_addr;
        L23_rd <= #2 L12_rd; /*stage 2*/
     end
    always @(posedge clk1) //stage 3
        begin
            regbank[L23_rd] <= #2 L23_Z; // Write back to register
            L34_Z <= #2 L23_Z; // Pass the result to the next stage
            L34_addr <= #2 L23_addr; // Pass the address
        end
    always @(negedge clk2) 
        begin
            $display("Memory[%3d] = %3d", L34_addr, L34_Z);
            mem[L34_addr] <= #2 L34_Z; // Write back to memory --stage 4
        end
endmodule

pipeline_test.v
`include "pipeline.v"
module pipe2_test;
    wire [7:0] z;
    reg [7:0] rs1, rs2, rd, func;
    reg [3:0] addr;
    reg clk1, clk2;
    integer k;
    pipeline_4 p4(z, rs1, rs2, rd, clk1, clk2, addr, func);
    initial begin
        clk1=0;
        clk2=0;
        repeat(20)
            begin
                #5 clk1=1; #5 clk1=0;
                #5 clk2=1; #5 clk2=0;
            end
    end
    
    initial
        for(k=0;k<16;k=k+1)
            p4.regbank[k] = k; // Initialize register bank
    initial
        for(k=0;k<256;k=k+1)
            p4.mem[k] = 8'b0; // Initialize memory with zeros
    initial begin
        #5 rs1=5; rs2=3; rd=10; func=0; addr=125;
        #20 rs1=3; rs2=2; rd=11; func=1; addr=126;
        #20 rs1=4; rs2=1; rd=12; func=2; addr=127;
        #20 rs1=2; rs2=5; rd=13; func=3; addr=128;
        #20 rs1=1; rs2=4; rd=14; func=4; addr=129;
        #20 rs1=0; rs2=6; rd=15; func=5; addr=130;
        #120;
        for(k=125;k<131;k=k+1)
           $display("Memory[%3d] = %3d", k, p4.mem[k]);
    end
    initial 
        begin
            $dumpfile("pipeline_test.vcd");
            $dumpvars(0, pipe2_test);
            #300;
            $finish;
        end
endmodule

pipeline_test.vcd
$date
	Sat Jul 26 00:34:05 2025
$end
$version
	Icarus Verilog
$end
$timescale
	1s
$end
$scope module pipe2_test $end
$var wire 8 ! z [7:0] $end
$var reg 4 " addr [3:0] $end
$var reg 1 # clk1 $end
$var reg 1 $ clk2 $end
$var reg 8 % func [7:0] $end
$var integer 32 & k [31:0] $end
$var reg 8 ' rd [7:0] $end
$var reg 8 ( rs1 [7:0] $end
$var reg 8 ) rs2 [7:0] $end
$scope module p4 $end
$var wire 4 * addr [3:0] $end
$var wire 1 + clk1 $end
$var wire 1 , clk2 $end
$var wire 8 - func [7:0] $end
$var wire 8 . rd [7:0] $end
$var wire 8 / rs1 [7:0] $end
$var wire 8 0 rs2 [7:0] $end
$var wire 8 1 zout [7:0] $end
$var reg 16 2 L12_A [15:0] $end
$var reg 16 3 L12_B [15:0] $end
$var reg 8 4 L12_addr [7:0] $end
$var reg 4 5 L12_func [3:0] $end
$var reg 4 6 L12_rd [3:0] $end
$var reg 16 7 L23_Z [15:0] $end
$var reg 8 8 L23_addr [7:0] $end
$var reg 4 9 L23_rd [3:0] $end
$var reg 16 : L34_Z [15:0] $end
$var reg 8 ; L34_addr [7:0] $end
$upscope $end
$upscope $end
$enddefinitions $end
#0
$dumpvars
bx ;
bx :
bx 9
bx 8
bx 7
bx 6
bx 5
bx 4
bx 3
bx 2
bx 1
bx 0
bx /
bx .
bx -
0,
0+
bx *
bx )
bx (
bx '
b100000000 &
bx %
0$
0#
bx "
bx !
$end
#2
b0 7
#5
b1101 "
b1101 *
b0 %
b0 -
b1010 '
b1010 .
b11 )
b11 0
b101 (
b101 /
1#
1+
#7
b0 !
b0 1
b0 5
b1101 4
b1010 6
b11 3
b101 2
b0 :
#10
0#
0+
#15
1$
1,
#20
0$
0,
#22
b1010 9
b1101 8
b1000 7
#25
1#
1+
b1110 "
b1110 *
b1 %
b1 -
b1011 '
b1011 .
b10 )
b10 0
b11 (
b11 /
#27
b1000 !
b1000 1
b1101 ;
b1000 :
b1 5
b1110 4
b1011 6
b10 3
b11 2
#30
0#
0+
#35
1$
1,
#40
0$
0,
#42
b1011 9
b1110 8
b1 7
#45
1#
1+
b1111 "
b1111 *
b10 %
b10 -
b1100 '
b1100 .
b1 )
b1 0
b100 (
b100 /
#47
b1 !
b1 1
b10 5
b1111 4
b1100 6
b1 3
b100 2
b1110 ;
b1 :
#50
0#
0+
#55
1$
1,
#60
0$
0,
#62
b1100 9
b1111 8
b0 7
#65
1#
1+
b0 "
b0 *
b11 %
b11 -
b1101 '
b1101 .
b101 )
b101 0
b10 (
b10 /
#67
b0 !
b0 1
b1111 ;
b0 :
b11 5
b0 4
b1101 6
b101 3
b10 2
#70
0#
0+
#75
1$
1,
#80
0$
0,
#82
b1101 9
b0 8
b10 7
#85
1#
1+
b1 "
b1 *
b100 %
b100 -
b1110 '
b1110 .
b100 )
b100 0
b1 (
b1 /
#87
b10 !
b10 1
b100 5
b1 4
b1110 6
b100 3
b1 2
b0 ;
b10 :
#90
0#
0+
#95
1$
1,
#100
0$
0,
#102
b1110 9
b1 8
b100 7
#105
1#
1+
b10 "
b10 *
b101 %
b101 -
b1111 '
b1111 .
b110 )
b110 0
b0 (
b0 /
#107
b100 !
b100 1
b1 ;
b100 :
b101 5
b10 4
b1111 6
b110 3
b0 2
#110
0#
0+
#115
1$
1,
#120
0$
0,
#122
b1111 9
b10 8
b1111111111111111 7
#125
1#
1+
#127
b11111111 !
b11111111 1
b10 ;
b1111111111111111 :
#130
0#
0+
#135
1$
1,
#140
0$
0,
#145
1#
1+
#150
0#
0+
#155
1$
1,
#160
0$
0,
#165
1#
1+
#170
0#
0+
#175
1$
1,
#180
0$
0,
#185
1#
1+
#190
0#
0+
#195
1$
1,
#200
0$
0,
#205
1#
1+
#210
0#
0+
#215
1$
1,
#220
0$
0,
#225
1#
1+
b10000011 &
